pyacclaim/__init__.py
pyacclaim/bone.py
pyacclaim/parser.py
pyacclaim-0.0.1.dist-info/METADATA
pyacclaim-0.0.1.dist-info/WHEEL
pyacclaim-0.0.1.dist-info/licenses/LICENSE
pyacclaim-0.0.1.dist-info/RECORD
