Metadata-Version: 2.1
Name: pyacclaim
Version: 0.0.1
Summary: A generic Acclaim motion capture data (AMC/ASF) parser.
Author-email: Stephen Baek <github@stephenbaek.com>
Project-URL: Homepage, https://github.com/stephenbaek/pyacclaim
Project-URL: Bug Tracker, https://github.com/stephenbaek/pyacclaim/issues
Classifier: Programming Language :: Python :: 3
Classifier: License :: OSI Approved :: MIT License
Classifier: Operating System :: OS Independent
Requires-Python: >=3.6
License-File: LICENSE
